[
  {
    "easy": [
      {
        "name": "Bot",
        "time": "3000"
      }
    ]
  },
  {
    "medium": [
      {
        "name": "Bot",
        "time": "3000"
      }
    ]
  },
  {
    "hard": [
      {
        "name": "Bot",
        "time": "30000"
      }
    ]
  },
  {
    "very-hard": [
      {
        "name": "Bot",
        "time": "30000"
      }
    ]
  },
  {
    "insane": [
      {
        "name": "Bot",
        "time": "30000"
      }
    ]
  },
  {
    "inhuman": [
      {
        "name": "Batya",
        "time": "420"
      }
    ]
  },
  {
    "inhuman": [
      {
        "name": "Bot",
        "time": "8000"
      }
    ]
  },
  {
    "easy": [
      {
        "name": "Bot",
        "time": "8000"
      }
    ]
  },
  {
    "easy": [
      {
        "name": "Dmitriy",
        "time": "6014"
      }
    ]
  },
  {
    "easy": [
      {
        "name": "Dmitrii",
        "time": "5963"
      }
    ]
  },
  {
    "easy": [
      {
        "name": "BodyMaker",
        "time": "5989"
      }
    ]
  },
  {
    "easy": [
      {
        "name": "Baracuda",
        "time": "222"
      }
    ]
  },
  {
    "easy": [
      {
        "name": "Good",
        "time": "81"
      }
    ]
  },
  {
    "easy": [
      {
        "name": "Howard Erman",
        "time": "500"
      }
    ]
  }
]